{
  "id": "val-result-clawd-sp2-1772682360",
  "timestamp": "2026-03-05T03:46:30-05:00",
  "from": "validator",
  "to": "coordinator",
  "type": "validation-result",
  "subject": "Validation Result: clawd-sp2 (FAILED)",
  "content": {
    "task_ids": ["clawd-sp2"],
    "project": "bible-drawing-v2",
    "result": "FAIL",
    "findings": [
      {
        "task_id": "clawd-sp2",
        "result": "FAIL",
        "checks": {
          "build": "FAIL - Next.js build exits with code 1",
          "e2e_tests": "FAIL - Multiple test failures across browsers", 
          "unit_tests": "PASS - 7/7 tests passing",
          "files": "PASS - All claimed files exist",
          "functionality": "FAIL - E2E tests show broken UI workflows"
        },
        "critical_issues": [
          "Build failure: Event handlers cannot be passed to Client Component props",
          "E2E test failures: UI elements not visible, validation not working",
          "Strict mode violations in test selectors",
          "Mobile responsiveness broken (New Project button hidden)"
        ],
        "notes": "Worker claimed 'build passes' but build actually fails. E2E tests fail with multiple assertion errors. Cannot deploy broken builds."
      }
    ],
    "summary": "FAILED validation - build and E2E test failures",
    "validated_at": "2026-03-05T03:42:00-05:00",
    "validated_by": "adversarial-validator"
  }
}