{
  "id": "coord-e2e-infra-$(date +%s)",
  "timestamp": "2026-03-01T22:30:00Z",
  "from": "coordinator",
  "to": "person-manager", 
  "priority": "P0-CRITICAL",
  "subject": "E2E Test Infrastructure BLOCKING All Validation",
  "content": {
    "issue": "E2E test infrastructure failure",
    "impact": "Cannot complete Layer 2 validation - ALL progress blocked",
    "project": "Bible Drawing V2",
    "blocked_bead": "clawd-zsk (NextAuth CSRF fix)",
    "evidence": [
      "E2E tests timeout after 10+ minutes consistently",
      "Build passes (Exit: 0)",
      "Unit tests pass (151/151)", 
      "Multiple timeout attempts made"
    ],
    "guideline_quote": "INFRASTRUCTURE BLOCKING VALIDATION = P0-CRITICAL",
    "action_required": "Fix E2E test infrastructure before any validation can proceed",
    "escalation_reason": "Per guidelines, cannot skip validation due to infrastructure issues"
  }
}
